nsp_ntfy/__init__.py
nsp_ntfy/app/__init__.py
nsp_ntfy/app/data/data_classes.py
nsp_ntfy/app/main.py
nsp_ntfy/entry.py
nsp_ntfy-2.0.2.dist-info/LICENSE
nsp_ntfy-2.0.2.dist-info/METADATA
nsp_ntfy-2.0.2.dist-info/WHEEL
nsp_ntfy-2.0.2.dist-info/entry_points.txt
nsp_ntfy-2.0.2.dist-info/RECORD
