Metadata-Version: 2.3
Name: nsp-ntfy
Version: 2.0.2
Summary: Monitor configurable MQTT topics and forward the messages to ntfy.sh topics.
License: MIT
Author: Joe McCarthy
Author-email: 179146301+joe-mccarthy@users.noreply.github.com
Maintainer: Joe McCarthy
Maintainer-email: 179146301+joe-mccarthy@users.noreply.github.com
Requires-Python: >=3.12
Classifier: License :: OSI Approved :: MIT License
Classifier: Programming Language :: Python :: 3
Classifier: Programming Language :: Python :: 3.12
Classifier: Programming Language :: Python :: 3.13
Requires-Dist: dataclass-wizard (>=0.35.0,<0.36.0)
Requires-Dist: paho-mqtt (>=2.1.0,<3.0.0)
Requires-Dist: requests (>=2.32.3,<3.0.0)
